README.md
setup.cfg
setup.py
AWS_OpenAPI_Lint.egg-info/PKG-INFO
AWS_OpenAPI_Lint.egg-info/SOURCES.txt
AWS_OpenAPI_Lint.egg-info/dependency_links.txt
AWS_OpenAPI_Lint.egg-info/entry_points.txt
AWS_OpenAPI_Lint.egg-info/requires.txt
AWS_OpenAPI_Lint.egg-info/top_level.txt
aws_openapi_lint/__init__.py
aws_openapi_lint/bcolors.py
aws_openapi_lint/rules/AuthorizerOnOptionsRule.py
aws_openapi_lint/rules/AuthorizerReferencedButMissingRule.py
aws_openapi_lint/rules/CORSInconsistentHeadersRule.py
aws_openapi_lint/rules/CORSNotEnoughVerbsRule.py
aws_openapi_lint/rules/ConflictingHttpVerbsRule.py
aws_openapi_lint/rules/IntegrationBaseUriRule.py
aws_openapi_lint/rules/MissingAmazonIntegrationRule.py
aws_openapi_lint/rules/NoCORSPresentRule.py
aws_openapi_lint/rules/PathParamNotMappedRule.py
aws_openapi_lint/rules/__init__.py
aws_openapi_lint/rules/rule_validator.py
aws_openapi_lint/rules/rules_helper.py
tests/__init__.py
tests/test_rule_validator.py