Metadata-Version: 2.1
Name: AWS-OpenAPI-Lint
Version: 0.2.0
Summary: AWS API Gateway OpenAPI spec linter
Home-page: https://github.com/evilmint/aws-openapi-lint
Author: Aleksander Lorenc
Author-email: lorencaleksander@gmail.com
License: MIT
Download-URL: https://github.com/evilmint/aws-openapi-lint/archive/0.2.0.tar.gz
Keywords: aws,openapi,linter
Platform: UNKNOWN
Classifier: Development Status :: 4 - Beta
Classifier: Intended Audience :: Developers
Classifier: Topic :: Software Development :: Build Tools
Classifier: License :: OSI Approved :: MIT License
Classifier: Programming Language :: Python :: 3
Requires-Python: >=3.6
